blipy/__init__.py
blipy/Http/__Lime.py
blipy/Http/__Postmaster.py
blipy/Http/__init__.py
blipy/Postmasters/__AI.py
blipy/Postmasters/__Analytics.py
blipy/Postmasters/__init__.py
blipy/Types/__Data.py
blipy/Types/__Date.py
blipy/Types/__Method.py
blipy/Types/__Response.py
blipy/Types/__Serializable.py
blipy/Types/__URI.py
blipy/Types/__init__.py
blipy-0.0.6.dist-info/LICENSE
blipy-0.0.6.dist-info/METADATA
blipy-0.0.6.dist-info/WHEEL
blipy-0.0.6.dist-info/top_level.txt
blipy-0.0.6.dist-info/RECORD
