Metadata-Version: 2.1
Name: blipy
Version: 0.0.6
Summary: Some BLiP functionalities right out of the box
Home-page: https://github.com/liviaalmeida/blipy
Author: Lívia Almeida
Author-email: leave.ah@gmail.com
License: UNKNOWN
Platform: UNKNOWN
Classifier: Programming Language :: Python :: 3
Classifier: License :: OSI Approved :: MIT License
Classifier: Operating System :: OS Independent
Requires-Python: >=3.6
